opgg/__init__.py
opgg/clients/__init__.py
opgg/clients/base_client.py
opgg/clients/internal_client.py
opgg/clients/meta_client.py
opgg/models/__init__.py
opgg/models/base_model.py
opgg/models/champion.py
opgg/models/match_history.py
opgg/models/meta_responses.py
opgg/models/shared.py
opgg/models/summoner_champion_stats.py
opgg_client-0.1.3.dist-info/METADATA
opgg_client-0.1.3.dist-info/WHEEL
opgg_client-0.1.3.dist-info/top_level.txt
opgg_client-0.1.3.dist-info/RECORD
